fastgoertzel/__init__.py
fastgoertzel/_fastgoertzel_core.cp312-win_amd64.pyd
fastgoertzel/_fastgoertzel_core.pyi
fastgoertzel-1.0.2.dist-info/licenses/LICENSE
fastgoertzel-1.0.2.dist-info/METADATA
fastgoertzel-1.0.2.dist-info/WHEEL
fastgoertzel-1.0.2.dist-info/top_level.txt
fastgoertzel-1.0.2.dist-info/RECORD
