Metadata-Version: 2.4
Name: fastgoertzel
Version: 1.0.2
Summary: High-performance Goertzel algorithm implementation
Home-page: https://github.com/0zean/fastgoertzel
Author: Nicholas Picini
Author-email: Nicholas Picini <pd1138@protonmail.com>
License: MIT
Classifier: Development Status :: 4 - Beta
Classifier: Programming Language :: Python :: 3
Classifier: Programming Language :: C++
Requires-Python: >=3.10
License-File: LICENSE
Requires-Dist: numpy>=2.2.6
Provides-Extra: test
Requires-Dist: pytest>=6.0; extra == "test"
Requires-Dist: pytest-benchmark; extra == "test"
Provides-Extra: dev
Requires-Dist: mypy; extra == "dev"
Requires-Dist: ruff; extra == "dev"
Dynamic: author
Dynamic: home-page
Dynamic: license-file
Dynamic: requires-python
